l3wtransformer/__init__.py
l3wtransformer/l3wtransformer.py
l3wtransformer-0.3.0.dist-info/METADATA
l3wtransformer-0.3.0.dist-info/RECORD
l3wtransformer-0.3.0.dist-info/WHEEL
l3wtransformer-0.3.0.dist-info/top_level.txt
