Metadata-Version: 2.1
Name: l3wtransformer
Version: 0.3.0
Summary: A word hashing method based on vectors of letter n-grams. Currently transforms text into sequences of numbers.
Home-page: https://github.com/GeorgesAlkhouri/l3wtransformer
Author: Georges Alkhouri
Author-email: georges.alkhouri@gmail.com
License: MIT
Keywords: machine-learning natural-language-processing preprocessing
Platform: UNKNOWN
Requires-Dist: nltk
Requires-Dist: pathos
Requires-Dist: numpy
Requires-Dist: pytest
